nexus_remoting/__init__.py
nexus_remoting/_encoder.py
nexus_remoting/_remoting.py
nexus_remoting-1.0.5.dist-info/METADATA
nexus_remoting-1.0.5.dist-info/WHEEL
nexus_remoting-1.0.5.dist-info/top_level.txt
nexus_remoting-1.0.5.dist-info/RECORD
