Metadata-Version: 2.1
Name: nexus-remoting
Version: 1.0.5
Summary: This package contains types to easily implement a Nexus.Sources.Remote client for the Nexus software (a GUI for time-series data lakes).
Home-page: https://github.com/malstroem-labs/nexus-sources-remote
Author: https://github.com/malstroem-labs
License: MIT
Project-URL: Project, https://malstroem-labs.github.io/Nexus
Project-URL: Repository, https://github.com/malstroem-labs/nexus-sources-remote
Keywords: Nexus time-series data lake remoting
Platform: any
Classifier: Programming Language :: Python :: 3
Classifier: License :: OSI Approved :: MIT License
Classifier: Operating System :: OS Independent
Requires-Python: >=3.9
Requires-Dist: nexus-extensibility (>=1.0.0)
